{
    "Function": [
        { "name": "Login", "id" : "000"},
        { "name": "Report - Summary Daily", "id" : "001"},
        { "name": "Report - Summary Monthly", "id" : "002"},
        { "name": "Report - Summary Supervisor", "id" : "003"},
        { "name": "Report - Summary Organization", "id" : "004"},
        { "name": "Report - Approve Allowance Report", "id" : "005"},
        { "name": "Report - Summary Adjust Report", "id" : "006"},
        { "name": "Engine - Control Batch", "id" : "007"},
        { "name": "Setup - ACC organization Path", "id" : "008"},
        { "name": "Setup - Special Day", "id" : "009"},
        { "name": "Setup - System Config", "id" : "010"},
        { "name": "Setup - User Role", "id" : "011"},
        { "name": "Setup - Welfare", "id" : "012"},
        { "name": "Setup - Keyword", "id" : "013"},
        { "name": "Setup - User Detail", "id" : "014"},
        { "name": "Setup - Max User's OT Compensation", "id" : "015"},
        { "name": "Setup - OT SAP Report", "id" : "016"}
    ],
    "local": {
        "Authorization": [
            {
                "00020180" : ["USER"]
            },
            {
                "00037262" : ["SUPER_USER"]
            },
            {
                "00040938" : ["ADMIN"]
            },
            {
                "00045912" : ["SUPER_ADMIN"]
            },
            {
                "00020061" : ["SUPER_USER", "ADMIN"]
            },
            {
                "00033122" : ["SUPER_ADMIN"]
            }
        ],
        "Role": [
            {
                "USER" : [
                    "000","001"
                ]
            },
            {
                "SUPER_USER" : [
                    "000","001","002","003","004","005","006","007"
                ]
            },
            {
                "ADMIN" : [
                    "000","008","009","010","011","012","013","014","015","016"
                ]
            },
            {
                "SUPER_ADMIN" : [
                    "000","001","002","003","004","005","006","007","008","009","010","011","012","013","014","015","016"
                ]
            }        
        ]
    },
    "development": {
        "Authorization": [
            {
                "00020180" : ["USER"]
            },
            {
                "00037262" : ["SUPER_USER"]
            },
            {
                "00040938" : ["ADMIN"]
            },
            {
                "00045912" : ["SUPER_ADMIN"]
            },
            {
                "00020061" : ["SUPER_USER", "ADMIN"]
            },
            {
                "00033122" : ["SUPER_ADMIN"]
            }
        ],
        "Role": [
            {
                "USER" : [
                    "000","001"
                ]
            },
            {
                "SUPER_USER" : [
                    "000","001","002","003","004","005","006","007"
                ]
            },
            {
                "ADMIN" : [
                    "000","008","009","010","011","012","013","014","015","016"
                ]
            },
            {
                "SUPER_ADMIN" : [
                    "000","001","002","003","004","005","006","007","008","009","010","011","012","013","014","015","016"
                ]
            }        
        ]
    },
    "staging": {
        "Authorization": [
            {
                "00020180" : ["USER"],
                "00037262" : ["SUPER_USER"],
                "00040938" : ["ADMIN"],
                "00045912" : ["SUPER_ADMIN"],
                "00020061" : ["SUPER_USER", "ADMIN"]
            }
        ],
        "Role": [
            {
                "USER" : [
                    "000","001"
                ]
            },
            {
                "SUPER_USER" : [
                    "000","001","002","003","004","005","006","007"
                ]
            },
            {
                "ADMIN" : [
                    "000","008","009","010","011","012","013","014","015","016"
                ]
            },
            {
                "SUPER_ADMIN" : [
                    "000","001","002","003","004","005","006","007","008","009","010","011","012","013","014","015","016"
                ]
            }        
        ]
    },
    "production": {
        "Authorization": [
            {
                "00020180" : ["USER"],
                "00037262" : ["SUPER_USER"],
                "00040938" : ["ADMIN"],
                "00045912" : ["SUPER_ADMIN"],
                "00020061" : ["SUPER_USER", "ADMIN"]
            }
        ],
        "Role": [
            {
                "USER" : [
                    "000","001"
                ]
            },
            {
                "SUPER_USER" : [
                    "000","001","002","003","004","005","006","007"
                ]
            },
            {
                "ADMIN" : [
                    "000","008","009","010","011","012","013","014","015","016"
                ]
            },
            {
                "SUPER_ADMIN" : [
                    "000","001","002","003","004","005","006","007","008","009","010","011","012","013","014","015","016"
                ]
            }        
        ]
    }    
}